pycond.py
pycond-20230212.dist-info/LICENSE
pycond-20230212.dist-info/METADATA
pycond-20230212.dist-info/WHEEL
pycond-20230212.dist-info/top_level.txt
pycond-20230212.dist-info/RECORD
