Metadata-Version: 2.1
Name: pycond
Version: 20230212
Summary: Lightweight Condition Parsing and Building of Evaluation Expressions
Home-page: https://github.com/axiros/pycond
Author: gk
Author-email: gk@axiros.com
License: BSD
Keywords: conditions,expression,async,serialization,rxpy,reactivex
Platform: UNKNOWN
Classifier: Development Status :: 5 - Production/Stable
Classifier: Intended Audience :: Developers
Classifier: Operating System :: POSIX
Classifier: License :: OSI Approved :: BSD License
Classifier: Topic :: Software Development :: Code Generators
Classifier: Topic :: Software Development :: Pre-processors
Classifier: Topic :: Text Editors :: Text Processing
Classifier: Programming Language :: Python :: 2
Classifier: Programming Language :: Python :: 2.7
Classifier: Programming Language :: Python :: 3
